LICENSE
README.rst
THIRD_PARTY_SOFTWARE.rst
surface_apps/__init__.py
surface_apps/driver.py
surface_apps/iso_surfaces/__init__.py
surface_apps/iso_surfaces/driver.py
surface_apps/iso_surfaces/params.py
surface_apps/iso_surfaces/utils.py
surface_apps-assets/__init__.py
surface_apps-assets/uijson/iso_surfaces.ui.json
surface_apps-0.1.0b1.dist-info/LICENSE
surface_apps-0.1.0b1.dist-info/METADATA
surface_apps-0.1.0b1.dist-info/WHEEL
surface_apps-0.1.0b1.dist-info/entry_points.txt
surface_apps-0.1.0b1.dist-info/RECORD
