Metadata-Version: 2.1
Name: surface-apps
Version: 0.1.0b1
Summary: Find Iso-surfaces in 3D data.
Home-page: https://www.mirageoscience.com/mining-industry-software/python-integration/
License: MIT
Author: Mira Geoscience
Author-email: support@mirageoscience.com
Maintainer: Benjamin Kary
Maintainer-email: benjamink@mirageoscience.com
Requires-Python: >=3.10,<4.0
Classifier: Development Status :: 2 - Pre-Alpha
Classifier: Intended Audience :: Science/Research
Classifier: License :: OSI Approved :: MIT License
Classifier: Natural Language :: English
Classifier: Operating System :: MacOS
Classifier: Operating System :: Microsoft :: Windows
Classifier: Operating System :: POSIX
Classifier: Operating System :: Unix
Classifier: Programming Language :: Python
Classifier: Programming Language :: Python :: 3
Classifier: Programming Language :: Python :: 3.10
Classifier: Programming Language :: Python :: 3.11
Classifier: Programming Language :: Python :: 3.12
Classifier: Programming Language :: Python :: 3.13
Classifier: Topic :: Scientific/Engineering
Classifier: Topic :: Scientific/Engineering :: Mathematics
Classifier: Topic :: Scientific/Engineering :: Physics
Requires-Dist: geoapps-utils (>=0.4.0b1,<0.5.0a.dev)
Requires-Dist: geoh5py (>=0.10.0b1,<0.11.0a.dev)
Requires-Dist: numpy (>=1.26.0,<1.27.0)
Requires-Dist: pydantic (>=2.5.2,<3.0.0)
Requires-Dist: scikit-image (==0.24.*)
Requires-Dist: scipy (>=1.14.0,<1.15.0)
Requires-Dist: tqdm (>=4.66.1,<4.67.0)
Project-URL: Repository, https://github.com/MiraGeoscience/surface-apps
